AUTHORS
CONTRIBUTING.md
LICENSE
MANIFEST.in
README.md
setup.cfg
setup.py
komapy/__init__.py
komapy/addons.py
komapy/axis.py
komapy/cache.py
komapy/chart.py
komapy/client.py
komapy/conf.py
komapy/constants.py
komapy/decorators.py
komapy/exceptions.py
komapy/extensions.py
komapy/layout.py
komapy/processing.py
komapy/series.py
komapy/settings.py
komapy/transforms.py
komapy/utils.py
komapy.egg-info/PKG-INFO
komapy.egg-info/SOURCES.txt
komapy.egg-info/dependency_links.txt
komapy.egg-info/not-zip-safe
komapy.egg-info/requires.txt
komapy.egg-info/top_level.txt