Metadata-Version: 2.1
Name: komapy
Version: 0.7.1
Summary: Python library for creating customizable BPPTKG Monitoring API chart
Home-page: https://gitlab.com/bpptkg/komapy
Author: Indra Rudianto
Author-email: indrarudianto.official@gmail.com
License: MIT
Platform: UNKNOWN
Classifier: Development Status :: 5 - Production/Stable
Classifier: Environment :: Console
Classifier: Operating System :: POSIX :: Linux
Classifier: Intended Audience :: Science/Research
Classifier: Natural Language :: English
Classifier: Programming Language :: Python :: 3.5
Classifier: Programming Language :: Python :: 3.6
Classifier: Programming Language :: Python :: 3.7
Classifier: Programming Language :: Python :: 3.8
